MANIFEST.in
README.md
setup.py
ask_amy/__init__.py
ask_amy/lambda_function.py
ask_amy.egg-info/PKG-INFO
ask_amy.egg-info/SOURCES.txt
ask_amy.egg-info/dependency_links.txt
ask_amy.egg-info/entry_points.txt
ask_amy.egg-info/not-zip-safe
ask_amy.egg-info/top_level.txt
ask_amy/cli/__init__.py
ask_amy/cli/cli_deploy.py
ask_amy/cli/command_line.py
ask_amy/cli/code_gen/__init__.py
ask_amy/cli/code_gen/jinja_code_generator.py
ask_amy/cli/code_gen/jinja_processing.py
ask_amy/cli/code_gen/templates/__init__.py
ask_amy/cli/code_gen/templates/alexa_lambda_role.json
ask_amy/cli/code_gen/templates/cli_config.tmpl
ask_amy/cli/code_gen/templates/dialog_model_intent_control.tmpl
ask_amy/cli/code_gen/templates/dialog_model_intents.tmpl
ask_amy/cli/code_gen/templates/dialog_model_master.tmpl
ask_amy/cli/code_gen/templates/dialog_model_slots.tmpl
ask_amy/cli/code_gen/templates/skill_code_master.tmpl
ask_amy/core/__init__.py
ask_amy/core/context.py
ask_amy/core/default_dialog.py
ask_amy/core/default_home_skill.py
ask_amy/core/dialog.py
ask_amy/core/directive.py
ask_amy/core/event.py
ask_amy/core/exceptions.py
ask_amy/core/object_dictionary.py
ask_amy/core/reply.py
ask_amy/core/request.py
ask_amy/core/session.py
ask_amy/core/skill_factory.py
ask_amy/database/__init__.py
ask_amy/database/database.py
ask_amy/services/__init__.py
ask_amy/services/address_service.py
ask_amy/services/service_base.py
ask_amy/state_mgr/__init__.py
ask_amy/state_mgr/stack_dialog_mgr.py
ask_amy/tests/__init__.py
ask_amy/tests/test_ask_amy_base.py
ask_amy/tests/cli/__init__.py
ask_amy/tests/cli/test_code_gen.py
ask_amy/tests/core/__init__.py
ask_amy/tests/core/test_dialog.py
ask_amy/tests/core/test_event.py
ask_amy/tests/core/test_reply.py
ask_amy/tests/core/test_request.py
ask_amy/tests/core/test_session.py
ask_amy/tests/database/__init__.py
ask_amy/tests/database/test_dynamo_db.py
ask_amy/tests/utilities/__init__.py
ask_amy/tests/utilities/test_time_of_day.py
ask_amy/utilities/__init__.py
ask_amy/utilities/account_link.py
ask_amy/utilities/iso_8601_validator.py
ask_amy/utilities/slot_validator.py
ask_amy/utilities/time_of_day.py
ask_amy/utilities/us_states.py