Metadata-Version: 1.0
Name: ask-amy
Version: 0.4.5
Summary: Python framework for Alexa Skill development
Home-page: https://github.com/dphiggs01/ask_amy
Author: Dan Higgins
Author-email: daniel.higgins@yahoo.com
License: MIT
Platform: UNKNOWN
